pysdcp_cteillet/__init__.py
pysdcp_cteillet/protocol.py
pysdcp_cteillet-0.0.4.dist-info/METADATA
pysdcp_cteillet-0.0.4.dist-info/WHEEL
pysdcp_cteillet-0.0.4.dist-info/licenses/LICENSE.md
pysdcp_cteillet-0.0.4.dist-info/RECORD
