Metadata-Version: 2.1
Name: pysdcp_cteillet
Version: 0.0.4
Summary: SDCP library to control Sony Projectors
Project-URL: Homepage, https://github.com/CTeillet/pySDCP
Project-URL: Issues, https://github.com/CTeillet/pySDCP/issues
Author-email: CTeillet <CTeillet@users.noreply.github.com>, Guy Shapira <Galala7@users.noreply.github.com>
License-File: LICENSE.md
Classifier: Development Status :: 4 - Beta
Classifier: License :: OSI Approved :: MIT License
Classifier: Operating System :: OS Independent
Classifier: Programming Language :: Python :: 3
Classifier: Topic :: Software Development :: Build Tools
Requires-Python: >=3
